dnsl-1.0.0.dist-info/licenses/LICENSE
dnslookup/__init__.py
dnslookup/main.py
dnsl-1.0.0.dist-info/METADATA
dnsl-1.0.0.dist-info/WHEEL
dnsl-1.0.0.dist-info/entry_points.txt
dnsl-1.0.0.dist-info/top_level.txt
dnsl-1.0.0.dist-info/RECORD
