Metadata-Version: 2.4
Name: dnsl
Version: 1.0.0
Summary: Advanced DNS Lookup Tool
Home-page: https://github.com/hemaabokila/dns_lookup
Author: Ibrahem abo kila
Author-email: ibrahemabokila@gmail.com
Classifier: Programming Language :: Python :: 3
Classifier: License :: OSI Approved :: MIT License
Classifier: Operating System :: OS Independent
Requires-Python: >=3.6
License-File: LICENSE
Requires-Dist: dnspython
Requires-Dist: requests
Requires-Dist: rich
Requires-Dist: colorama
Requires-Dist: pyfiglet
Dynamic: author
Dynamic: author-email
Dynamic: classifier
Dynamic: description
Dynamic: description-content-type
Dynamic: home-page
Dynamic: license-file
Dynamic: requires-dist
Dynamic: requires-python
Dynamic: summary
